srsgui/__init__.py
srsgui/__main__.py
srsgui/examples/oscilloscope example/oscilloscope example project.taskconfig
srsgui/examples/oscilloscope example/instruments/cg635.py
srsgui/examples/oscilloscope example/instruments/sds1202.py
srsgui/examples/oscilloscope example/tasks/captured_fft.py
srsgui/examples/oscilloscope example/tasks/identify.py
srsgui/examples/oscilloscope example/tasks/plot_example.py
srsgui/examples/oscilloscope example/tasks/scope_capture.py
srsgui/examples/oscilloscope example/tasks/simulated_fft.py
srsgui/inst/__init__.py
srsgui/inst/commands.py
srsgui/inst/component.py
srsgui/inst/exceptions.py
srsgui/inst/indexcommands.py
srsgui/inst/instrument.py
srsgui/inst/communications/__init__.py
srsgui/inst/communications/interface.py
srsgui/inst/communications/serial_ports.py
srsgui/inst/communications/serialinterface.py
srsgui/inst/communications/tcpipinterface.py
srsgui/plots/__init__.py
srsgui/plots/timeplot.py
srsgui/task/__init__.py
srsgui/task/callbacks.py
srsgui/task/config.py
srsgui/task/inputs.py
srsgui/task/sessionhandler.py
srsgui/task/task.py
srsgui/task/taskresult.py
srsgui/ui/__init__.py
srsgui/ui/commandhandler.py
srsgui/ui/commandterminal.py
srsgui/ui/connectdlg.py
srsgui/ui/deviceinfohandler.py
srsgui/ui/dockhandler.py
srsgui/ui/inputpanel.py
srsgui/ui/qtloghandler.py
srsgui/ui/resource.qrc
srsgui/ui/resource_rc.py
srsgui/ui/signalhandler.py
srsgui/ui/srslogo.jpg
srsgui/ui/stdout.py
srsgui/ui/taskmain.py
srsgui/ui/taskmain.ui
srsgui/ui/ui_taskmain.py
srsgui/ui/commandtree/__init__.py
srsgui/ui/commandtree/commanddelegate.py
srsgui/ui/commandtree/commandhandler.py
srsgui/ui/commandtree/commanditem.py
srsgui/ui/commandtree/commandmodel.py
srsgui/ui/commandtree/commandspinbox.py
srsgui/ui/commandtree/commandtreeview.py
srsgui/ui/commandtree/commandtreewidget.py
srsgui/ui/commandtree/ui_commandtreewidget.py
srsgui/ui/qt/QtCore.py
srsgui/ui/qt/QtGui.py
srsgui/ui/qt/QtWidgets.py
srsgui/ui/qt/__init__.py
srsgui-0.4.6.dist-info/LICENSE.txt
srsgui-0.4.6.dist-info/METADATA
srsgui-0.4.6.dist-info/WHEEL
srsgui-0.4.6.dist-info/entry_points.txt
srsgui-0.4.6.dist-info/top_level.txt
srsgui-0.4.6.dist-info/RECORD
