Metadata-Version: 2.1
Name: srsgui
Version: 0.4.6
Summary: Framework to run instrument-controlling Python scripts in GUI
Author: Chulhoon Kim
License: MIT license
Project-URL: homepage, https://github.com/thinkSRS/srsgui
Project-URL: repository, https://github.com/thinkSRS/srsgui.git
Project-URL: documentation, https://thinksrs.github.io/srsgui
Project-URL: changelog, https://thinksrs.github.io/srsgui/changelog.html
Keywords: instrument control,data acquisition,data visualization
Classifier: Development Status :: 4 - Beta
Classifier: Intended Audience :: Science/Research
Classifier: License :: OSI Approved :: MIT License
Classifier: Programming Language :: Python :: 3.7
Classifier: Programming Language :: Python :: 3.8
Classifier: Programming Language :: Python :: 3.9
Classifier: Programming Language :: Python :: 3.10
Classifier: Topic :: Scientific/Engineering
Requires-Python: >=3.7
License-File: LICENSE.txt
Requires-Dist: pyserial >=3
Provides-Extra: docs
Requires-Dist: matplotlib ; extra == 'docs'
Requires-Dist: pyside2 ; extra == 'docs'
Requires-Dist: sphinx >=5 ; extra == 'docs'
Requires-Dist: sphinx-rtd-theme >=1 ; extra == 'docs'
Provides-Extra: full
Requires-Dist: matplotlib >=3.6.2 ; extra == 'full'
Requires-Dist: pyside6 ; extra == 'full'
